sparcur/__init__.py
sparcur/auth-config.py
sparcur/backends.py
sparcur/cli.py
sparcur/config.py
sparcur/converters.py
sparcur/core.py
sparcur/curation.py
sparcur/dashboard_server.py
sparcur/datasets.py
sparcur/datasources.py
sparcur/derives.py
sparcur/exceptions.py
sparcur/mapping.py
sparcur/metastore.py
sparcur/monkey.py
sparcur/normalization.py
sparcur/paths.py
sparcur/pennsieve_api.py
sparcur/pipelines.py
sparcur/protocols.py
sparcur/raw_json.py
sparcur/reports.py
sparcur/schemas.py
sparcur/server.py
sparcur/sheets.py
sparcur/state.py
sparcur/utils.py
sparcur/export/__init__.py
sparcur/export/core.py
sparcur/export/disco.py
sparcur/export/published.py
sparcur/export/reprotcur.py
sparcur/export/triples.py
sparcur/export/xml.py
sparcur/extract/__init__.py
sparcur/extract/xml.py
sparcur/simple/__init__.py
sparcur/simple/clean_metadata_files.py
sparcur/simple/clone.py
sparcur/simple/combine.py
sparcur/simple/compact.py
sparcur/simple/disco.py
sparcur/simple/export.py
sparcur/simple/extract.py
sparcur/simple/fetch.py
sparcur/simple/fetch_annotations.py
sparcur/simple/fetch_file.py
sparcur/simple/fetch_files.py
sparcur/simple/fetch_metadata_files.py
sparcur/simple/fetch_remote_metadata.py
sparcur/simple/fetch_remote_metadata_all.py
sparcur/simple/fetch_secondary.py
sparcur/simple/path_data.py
sparcur/simple/path_metadata.py
sparcur/simple/path_metadata_validate.py
sparcur/simple/pull.py
sparcur/simple/retrieve.py
sparcur/simple/transform.py
sparcur/simple/utils.py
sparcur/simple/validate.py
sparcur/sparcron/__init__.py
sparcur/sparcron/__main__.py
sparcur/sparcron/core.py
sparcur/sparcron/endpoints.py
sparcur/sparcron/server.py
sparcur/sparcron/status.py
sparcur-0.0.1.dev5.data/data/share/sparcur/resources/mimetypes.json
sparcur-0.0.1.dev5.dist-info/LICENSE
sparcur-0.0.1.dev5.dist-info/METADATA
sparcur-0.0.1.dev5.dist-info/WHEEL
sparcur-0.0.1.dev5.dist-info/entry_points.txt
sparcur-0.0.1.dev5.dist-info/top_level.txt
sparcur-0.0.1.dev5.dist-info/RECORD
