Metadata-Version: 2.1
Name: sparcur
Version: 0.0.1.dev5
Summary: assorted
Home-page: https://github.com/SciCrunch/sparc-curation
Author: Tom Gillespie
Author-email: tgbugs@gmail.com
License: MIT
Keywords: SPARC curation biocuration ontology pennsieve protc protocols hypothesis
Classifier: Development Status :: 3 - Alpha
Classifier: License :: OSI Approved :: MIT License
Classifier: Programming Language :: Python :: 3.6
Classifier: Programming Language :: Python :: 3.7
Classifier: Programming Language :: Python :: 3.8
Classifier: Programming Language :: Python :: 3.9
Classifier: Programming Language :: Python :: 3.10
Classifier: Programming Language :: Python :: 3.11
Classifier: Programming Language :: Python :: Implementation :: CPython
Classifier: Programming Language :: Python :: Implementation :: PyPy
Classifier: Operating System :: POSIX :: Linux
Classifier: Operating System :: MacOS :: MacOS X
Classifier: Operating System :: Microsoft :: Windows
Requires-Python: >=3.6
License-File: LICENSE
Requires-Dist: augpathlib (>=0.0.25)
Requires-Dist: beautifulsoup4
Requires-Dist: pennsieve
Requires-Dist: dicttoxml
Requires-Dist: jsonschema (>=3.0.1)
Requires-Dist: ontquery (>=0.2.8)
Requires-Dist: openpyxl
Requires-Dist: protcur (>=0.0.11)
Requires-Dist: pyontutils (>=0.1.32)
Requires-Dist: pysercomb (>=0.0.11)
Requires-Dist: terminaltables
Requires-Dist: xlsx2csv
Requires-Dist: ipython ; python_version < "3.7"
Provides-Extra: cron
Requires-Dist: celery ; extra == 'cron'
Requires-Dist: redis ; extra == 'cron'
Provides-Extra: dev
Requires-Dist: wheel ; extra == 'dev'
Provides-Extra: filetypes
Requires-Dist: nibabel ; extra == 'filetypes'
Requires-Dist: pydicom ; extra == 'filetypes'
Requires-Dist: scipy ; extra == 'filetypes'
Provides-Extra: test
Requires-Dist: pytest ; extra == 'test'
Requires-Dist: pytest-runner ; extra == 'test'
Requires-Dist: celery ; extra == 'test'
Requires-Dist: redis ; extra == 'test'
